bayes_yplus/__init__.py
bayes_yplus/_version.py
bayes_yplus/utils.py
bayes_yplus/yplus_model.py
bayes_yplus-1.3.2.dist-info/LICENSE
bayes_yplus-1.3.2.dist-info/METADATA
bayes_yplus-1.3.2.dist-info/WHEEL
bayes_yplus-1.3.2.dist-info/top_level.txt
bayes_yplus-1.3.2.dist-info/RECORD
