Metadata-Version: 2.2
Name: bayes_yplus
Version: 1.3.2
Summary: A Bayesian Model of Radio Recombination Line Emission
Home-page: https://github.com/tvwenger/bayes_yplus
Author: Trey V. Wenger
Author-email: Trey Wenger <tvwenger@gmail.com>
License: The MIT License (MIT)
Project-URL: Homepage, https://github.com/tvwenger/bayes_yplus
Classifier: Programming Language :: Python :: 3
Classifier: License :: OSI Approved :: GNU General Public License v3 (GPLv3)
Classifier: Operating System :: OS Independent
Requires-Python: >=3.11
License-File: LICENSE
Requires-Dist: bayes_spec>=1.7.2
Dynamic: author
Dynamic: home-page
Dynamic: requires-python
